zepben/edith/__init__.py
zepben/edith/linecode_catalogue.py
zepben/edith/transformer_catalogue.py
zepben.edith-0.4.0.dist-info/LICENSE
zepben.edith-0.4.0.dist-info/METADATA
zepben.edith-0.4.0.dist-info/WHEEL
zepben.edith-0.4.0.dist-info/top_level.txt
zepben.edith-0.4.0.dist-info/RECORD
