Metadata-Version: 2.1
Name: zepben.edith
Version: 0.4.0
Summary: Python SDK extensions for the Edith project
Home-page: https://github.com/zepben/edith-sdk
Author: Kurt Greaves
Author-email: kurt.greaves@zepben.com
License: MPL 2.0
Classifier: License :: OSI Approved :: Mozilla Public License 2.0 (MPL 2.0)
Classifier: Programming Language :: Python :: 3
Classifier: Programming Language :: Python :: 3.9
Classifier: Programming Language :: Python :: 3.10
Classifier: Operating System :: OS Independent
Requires-Python: >=3.9
License-File: LICENSE
Requires-Dist: zepben.evolve <0.38.0,>=0.37.0
Requires-Dist: dataclassy ==0.6.2
Provides-Extra: test
Requires-Dist: pytest ==7.1.2 ; extra == 'test'
Requires-Dist: pytest-cov ==2.10.1 ; extra == 'test'
Requires-Dist: pytest-asyncio ==0.19.0 ; extra == 'test'
Requires-Dist: pytest-timeout ==1.4.2 ; extra == 'test'
Requires-Dist: grpcio-testing ==1.57.0 ; extra == 'test'
Requires-Dist: pylint ==2.14.5 ; extra == 'test'
